setup.py
kopy/__init__.py
kopy/kopy.py
kopy.egg-info/PKG-INFO
kopy.egg-info/SOURCES.txt
kopy.egg-info/dependency_links.txt
kopy.egg-info/not-zip-safe
kopy.egg-info/requires.txt
kopy.egg-info/top_level.txt
kopy/funcs/__init__.py
kopy/funcs/kopy_func.py
kopy/funcs/utils.py
kopy/funcs/database/bigram.json
kopy/funcs/database/posFreq.json
kopy/funcs/database/posList.json
kopy/funcs/database/posbigram.json
kopy/funcs/database/tagFreq.json
kopy/funcs/database/verbchange.json