Metadata-Version: 1.1
Name: kopy
Version: 1.5
Summary: A Pure Python Korean Analyzer
Home-page: https://github.com/biggydog/kopy
Author: BeomSeok Lee(BiggyDog)
Author-email: bums00084@gmail.com
License: GPL v3.0
Download-URL: https://github.com/BiggyDog/kopy/archive/v1.5.tar.gz
Keywords: Korean Analyzer,Korean,NLP
Platform: UNKNOWN
Classifier: Development Status :: 3 - Alpha
Classifier: Intended Audience :: Developers
Classifier: Topic :: Software Development :: Build Tools
Classifier: Operating System :: MacOS
Classifier: Operating System :: POSIX :: Linux
Classifier: License :: OSI Approved :: GNU General Public License v3 or later (GPLv3+)
Classifier: Programming Language :: Python :: 3.5
Classifier: Programming Language :: Python :: 2.7
